README.rst
setup.py
sentry_plivo/__init__.py
sentry_plivo/plugin.py
sentry_plivo.egg-info/PKG-INFO
sentry_plivo.egg-info/SOURCES.txt
sentry_plivo.egg-info/dependency_links.txt
sentry_plivo.egg-info/entry_points.txt
sentry_plivo.egg-info/not-zip-safe
sentry_plivo.egg-info/pbr.json
sentry_plivo.egg-info/requires.txt
sentry_plivo.egg-info/top_level.txt