Metadata-Version: 1.0
Name: sentry-plivo
Version: 0.1
Summary: A Sentry plugin for sending SMS notifications via Plivo.
Home-page: https://github.com/dash1291/sentry-plivo
Author: Ashish Dubey
Author-email: ashish.dubey91@gmail.com
License: MIT
Platform: UNKNOWN
